{
  "law_sources": {
    "name": "نظام الدفاتر التجارية",
    "type": "law",
    "jurisdiction": "المملكة العربية السعودية",
    "issuing_authority": "المرسوم الملكي رقم (م/61) بتاريخ 17 / 12 / 1409هـ",
    "issue_date": "1409/12/17هـ",
    "description": "ينظم هذا النظام التزامات التجار بمسك الدفاتر التجارية، ويحدد أنواعها وشروط تنظيمها وحفظها، وآثارها القانونية والعقوبات المترتبة على مخالفة أحكامها.",
    "status": "processed",
    "source_url": "https://laws.boe.gov.sa/BoeLaws/Laws/LawDetails/05690bd6-2c75-4b65-a148-a9a700f1bccf/1",
    "articles": [
      {
        "article": "المادة 1",
        "text": "يجب على كل تاجر أن يمسك الدفاتر التجارية التي تستلزمها طبيعة تجارته وأهميتها بطريقة تكفل بيان مركزه المالي بدقة. وتشمل على الأقل دفتر اليومية الأصلي ودفتر الجرد ودفتر الأستاذ العام. ويعفى من ذلك من لا يزيد رأس ماله على مائة ألف ريال.",
        "keywords": ["دفاتر تجارية", "دفتر اليومية", "دفتر الجرد", "دفتر الأستاذ", "التزامات التاجر"],
        "order_index": 1
      },
      {
        "article": "المادة 2",
        "text": "يجوز أن تدون البيانات الخاصة بالدفاتر التجارية عن طريق الحاسب الآلي، وفق الإجراءات التي تحددها اللائحة التنفيذية لضمان سلامة البيانات.",
        "keywords": ["الحاسب الآلي", "الدفاتر الإلكترونية", "اللائحة التنفيذية"],
        "order_index": 2
      },
      {
        "article": "المادة 3",
        "text": "تقيد في دفتر اليومية جميع العمليات المالية والمصروفات والإيرادات اليومية بالتفصيل. ويجوز استعمال دفاتر مساعدة لإثبات التفاصيل مع نقل الإجماليات إلى دفتر اليومية الأصلي.",
        "keywords": ["دفتر اليومية", "عمليات مالية", "دفاتر مساعدة", "قيود"],
        "order_index": 3
      },
      {
        "article": "المادة 4",
        "text": "تقيد في دفتر الجرد تفاصيل البضاعة الموجودة في نهاية السنة المالية وصورة من قائمة المركز المالي للتاجر.",
        "keywords": ["دفتر الجرد", "المركز المالي", "البضاعة"],
        "order_index": 4
      },
      {
        "article": "المادة 5",
        "text": "ترحل العمليات المالية ذات الطبيعة الواحدة من دفتر اليومية إلى دفتر الأستاذ العام بحيث يمكن استخلاص نتيجة كل حساب بسهولة.",
        "keywords": ["دفتر الأستاذ العام", "الترحيل", "العمليات المالية"],
        "order_index": 5
      },
      {
        "article": "المادة 6",
        "text": "على التاجر أن يحتفظ بصورة من جميع المراسلات والوثائق المتعلقة بتجارته الصادرة والواردة، بطريقة منتظمة تسهل مراجعة القيود الحسابية والتحقق من الأرباح والخسائر.",
        "keywords": ["حفظ المراسلات", "الوثائق التجارية", "الأرباح والخسائر"],
        "order_index": 6
      },
      {
        "article": "المادة 7",
        "text": "يجب أن تكون الدفاتر وفق النموذج الذي تحدده وزارة التجارة وأن تكون صفحاتها مرقمة.",
        "keywords": ["وزارة التجارة", "النماذج", "ترقيم الصفحات"],
        "order_index": 7
      },
      {
        "article": "المادة 8",
        "text": "على التاجر وورثته الاحتفاظ بالدفاتر والمراسلات والمستندات لمدة عشر سنوات على الأقل.",
        "keywords": ["مدة الحفظ", "الورثة", "الدفاتر التجارية"],
        "order_index": 8
      },
      {
        "article": "المادة 9",
        "text": "يفترض أن جميع القيود المدونة في دفاتر التاجر قد دونت بعلمه ورضاه ما لم يثبت العكس.",
        "keywords": ["القرينة القانونية", "القيود التجارية", "الإثبات"],
        "order_index": 9
      },
      {
        "article": "المادة 10",
        "text": "للقاضي أن يأمر بتقديم الدفاتر التجارية لفحص القيود المتعلقة بالنزاع. ويعد امتناع التاجر قرينة على صحة الوقائع المطلوب إثباتها.",
        "keywords": ["المحكمة", "فحص الدفاتر", "الإثبات القضائي"],
        "order_index": 10
      },
      {
        "article": "المادة 11",
        "text": "يتولى ضبط مخالفات النظام موظفون يصدر بتعيينهم قرار من وزير التجارة.",
        "keywords": ["ضبط المخالفات", "وزارة التجارة", "الموظفون المختصون"],
        "order_index": 11
      },
      {
        "article": "المادة 12",
        "text": "يعاقب كل من يخالف أحكام هذا النظام أو لوائحه بغرامة لا تقل عن خمسة آلاف ريال ولا تزيد على خمسين ألف ريال.",
        "keywords": ["العقوبات", "غرامة مالية", "مخالفات النظام"],
        "order_index": 12
      },
      {
        "article": "المادة 13",
        "text": "يختص ديوان المظالم بتوقيع العقوبات المنصوص عليها في النظام.",
        "keywords": ["ديوان المظالم", "الاختصاص القضائي", "العقوبات"],
        "order_index": 13
      },
      {
        "article": "المادة 14",
        "text": "تلغى المواد (6، 7، 8، 9، 10) من نظام المحكمة التجارية وكل حكم يتعارض مع أحكام هذا النظام.",
        "keywords": ["الإلغاء", "نظام المحكمة التجارية"],
        "order_index": 14
      },
      {
        "article": "المادة 15",
        "text": "على وزير التجارة إصدار اللوائح والقرارات اللازمة لتنفيذ هذا النظام.",
        "keywords": ["اللائحة التنفيذية", "وزير التجارة"],
        "order_index": 15
      },
      {
        "article": "المادة 16",
        "text": "ينشر هذا النظام في الجريدة الرسمية، ويعمل به بعد ستة أشهر من تاريخ نشره.",
        "keywords": ["تاريخ النفاذ", "الجريدة الرسمية", "النشر"],
        "order_index": 16
      }
    ]
  }
}